twwt/__init__.py
twwt/cleaner.py
twwt-0.0.2.dist-info/LICENSE
twwt-0.0.2.dist-info/METADATA
twwt-0.0.2.dist-info/WHEEL
twwt-0.0.2.dist-info/top_level.txt
twwt-0.0.2.dist-info/RECORD
